{"time" : "2024-02-26 13:20:43", "model" : "Acurite-515", "id" : 86, "channel" : "AR", "battery_ok" : 1, "temperature_F" : 71.800, "mic" : "CHECKSUM"}
{"time" : "2024-02-26 13:20:43", "model" : "Acurite-515", "id" : 86, "channel" : "AR", "battery_ok" : 1, "temperature_F" : 71.800, "mic" : "CHECKSUM"}
{"time" : "2024-02-26 13:20:43", "model" : "Acurite-515", "id" : 86, "channel" : "AR", "battery_ok" : 1, "temperature_F" : 71.800, "mic" : "CHECKSUM"}
{"time" : "2024-02-26 13:21:12", "model" : "Acurite-515", "id" : 216, "channel" : "AF", "battery_ok" : 1, "temperature_F" : 4.600, "mic" : "CHECKSUM"}
{"time" : "2024-02-26 13:21:12", "model" : "Acurite-515", "id" : 216, "channel" : "AF", "battery_ok" : 1, "temperature_F" : 4.600, "mic" : "CHECKSUM"}
{"time" : "2024-02-26 13:21:12", "model" : "Acurite-515", "id" : 216, "channel" : "AF", "battery_ok" : 1, "temperature_F" : 4.600, "mic" : "CHECKSUM"}
{"time" : "2024-02-26 13:21:44", "model" : "Acurite-515", "id" : 86, "channel" : "AR", "battery_ok" : 1, "temperature_F" : 71.800, "mic" : "CHECKSUM"}
{"time" : "2024-02-26 13:21:44", "model" : "Acurite-515", "id" : 86, "channel" : "AR", "battery_ok" : 1, "temperature_F" : 71.800, "mic" : "CHECKSUM"}
{"time" : "2024-02-26 13:21:44", "model" : "Acurite-515", "id" : 86, "channel" : "AR", "battery_ok" : 1, "temperature_F" : 71.800, "mic" : "CHECKSUM"}
{"time" : "2024-02-26 13:22:12", "model" : "Acurite-515", "id" : 216, "channel" : "AF", "battery_ok" : 1, "temperature_F" : 4.800, "mic" : "CHECKSUM"}
{"time" : "2024-02-26 13:22:12", "model" : "Acurite-515", "id" : 216, "channel" : "AF", "battery_ok" : 1, "temperature_F" : 4.800, "mic" : "CHECKSUM"}
{"time" : "2024-02-26 13:22:12", "model" : "Acurite-515", "id" : 216, "channel" : "AF", "battery_ok" : 1, "temperature_F" : 4.800, "mic" : "CHECKSUM"}
{"time" : "2024-02-26 13:22:45", "model" : "Acurite-515", "id" : 86, "channel" : "AR", "battery_ok" : 1, "temperature_F" : 71.800, "mic" : "CHECKSUM"}
{"time" : "2024-02-26 13:22:45", "model" : "Acurite-515", "id" : 86, "channel" : "AR", "battery_ok" : 1, "temperature_F" : 71.800, "mic" : "CHECKSUM"}
{"time" : "2024-02-26 13:22:45", "model" : "Acurite-515", "id" : 86, "channel" : "AR", "battery_ok" : 1, "temperature_F" : 71.800, "mic" : "CHECKSUM"}
{"time" : "2024-02-26 13:23:12", "model" : "Acurite-515", "id" : 216, "channel" : "AF", "battery_ok" : 1, "temperature_F" : 5.000, "mic" : "CHECKSUM"}
{"time" : "2024-02-26 13:23:12", "model" : "Acurite-515", "id" : 216, "channel" : "AF", "battery_ok" : 1, "temperature_F" : 5.000, "mic" : "CHECKSUM"}
{"time" : "2024-02-26 13:23:12", "model" : "Acurite-515", "id" : 216, "channel" : "AF", "battery_ok" : 1, "temperature_F" : 5.000, "mic" : "CHECKSUM"}
{"time" : "2024-02-26 13:23:46", "model" : "Acurite-515", "id" : 86, "channel" : "AR", "battery_ok" : 1, "temperature_F" : 71.800, "mic" : "CHECKSUM"}
{"time" : "2024-02-26 13:23:46", "model" : "Acurite-515", "id" : 86, "channel" : "AR", "battery_ok" : 1, "temperature_F" : 71.800, "mic" : "CHECKSUM"}
{"time" : "2024-02-26 13:23:46", "model" : "Acurite-515", "id" : 86, "channel" : "AR", "battery_ok" : 1, "temperature_F" : 71.800, "mic" : "CHECKSUM"}
